gs.dmarc-2.1.9-py2.7-nspkg.pth
gs/dmarc/__init__.py
gs/dmarc/lookup.py
gs/dmarc/suffixlist.txt
gs/dmarc/tests/__init__.py
gs/dmarc/tests/lookup.py
gs/dmarc/tests/receiver.py
gs/dmarc/tests/test_all.py
gs.dmarc-2.1.9.dist-info/DESCRIPTION.rst
gs.dmarc-2.1.9.dist-info/METADATA
gs.dmarc-2.1.9.dist-info/RECORD
gs.dmarc-2.1.9.dist-info/WHEEL
gs.dmarc-2.1.9.dist-info/entry_points.txt
gs.dmarc-2.1.9.dist-info/metadata.json
gs.dmarc-2.1.9.dist-info/namespace_packages.txt
gs.dmarc-2.1.9.dist-info/top_level.txt
