Metadata-Version: 2.0
Name: gs.dmarc
Version: 2.1.9
Summary: Look up and report on the DMARC status of a domain.
Home-page: https://github.com/groupserver/gs.dmarc
Author: Michael JasonSmith
Author-email: mpj17@onlinegroups.net
License: ZPL 2.1
Keywords: DKIM,SPF,DMARC,email,RFC 7489,RFC 6376,RFC 4408
Platform: UNKNOWN
Classifier: Development Status :: 4 - Beta
Classifier: Intended Audience :: Developers
Classifier: License :: OSI Approved :: Zope Public License
Classifier: Natural Language :: English
Classifier: Operating System :: OS Independent
Classifier: Programming Language :: Python
Classifier: Programming Language :: Python :: 2
Classifier: Programming Language :: Python :: 2.7
Classifier: Programming Language :: Python :: 3
Classifier: Programming Language :: Python :: 3.3
Classifier: Programming Language :: Python :: 3.4
Classifier: Programming Language :: Python :: 3.5
Classifier: Programming Language :: Python :: Implementation :: CPython
Classifier: Programming Language :: Python :: Implementation :: PyPy
Classifier: Topic :: Software Development :: Libraries :: Python Modules
Requires-Dist: dnspython (>=1.11.1)
Requires-Dist: enum34
Requires-Dist: publicsuffix
Requires-Dist: setuptools
Provides-Extra: docs
Requires-Dist: Sphinx; extra == 'docs'
